thousandeyes_sdk/endpoint_tests/__init__.py
thousandeyes_sdk/endpoint_tests/py.typed
thousandeyes_sdk/endpoint_tests/api/__init__.py
thousandeyes_sdk/endpoint_tests/api/agent_to_server_endpoint_dynamic_tests_api.py
thousandeyes_sdk/endpoint_tests/api/agent_to_server_endpoint_scheduled_tests_api.py
thousandeyes_sdk/endpoint_tests/api/endpoint_scheduled_tests_api.py
thousandeyes_sdk/endpoint_tests/api/http_server_endpoint_scheduled_tests_api.py
thousandeyes_sdk/endpoint_tests/models/__init__.py
thousandeyes_sdk/endpoint_tests/models/dynamic_test.py
thousandeyes_sdk/endpoint_tests/models/dynamic_test_links.py
thousandeyes_sdk/endpoint_tests/models/dynamic_test_request.py
thousandeyes_sdk/endpoint_tests/models/dynamic_test_self_link.py
thousandeyes_sdk/endpoint_tests/models/dynamic_tests.py
thousandeyes_sdk/endpoint_tests/models/endpoint_agent_labels_selector_config.py
thousandeyes_sdk/endpoint_tests/models/endpoint_agent_selector_config.py
thousandeyes_sdk/endpoint_tests/models/endpoint_agent_to_server_instant_test.py
thousandeyes_sdk/endpoint_tests/models/endpoint_agent_to_server_test.py
thousandeyes_sdk/endpoint_tests/models/endpoint_agent_to_server_test_request.py
thousandeyes_sdk/endpoint_tests/models/endpoint_agent_to_server_tests.py
thousandeyes_sdk/endpoint_tests/models/endpoint_all_agents_selector_config.py
thousandeyes_sdk/endpoint_tests/models/endpoint_dynamic_test_update.py
thousandeyes_sdk/endpoint_tests/models/endpoint_http_server_base_test.py
thousandeyes_sdk/endpoint_tests/models/endpoint_http_server_instant_test.py
thousandeyes_sdk/endpoint_tests/models/endpoint_http_server_test.py
thousandeyes_sdk/endpoint_tests/models/endpoint_http_server_test_request.py
thousandeyes_sdk/endpoint_tests/models/endpoint_http_server_tests.py
thousandeyes_sdk/endpoint_tests/models/endpoint_http_test_update.py
thousandeyes_sdk/endpoint_tests/models/endpoint_instant_test.py
thousandeyes_sdk/endpoint_tests/models/endpoint_ip_version_in.py
thousandeyes_sdk_endpoint_tests-2.23.0.dist-info/licenses/LICENSE
thousandeyes_sdk_endpoint_tests-2.23.0.dist-info/licenses/NOTICE
thousandeyes_sdk_endpoint_tests-2.23.0.dist-info/METADATA
thousandeyes_sdk_endpoint_tests-2.23.0.dist-info/WHEEL
thousandeyes_sdk_endpoint_tests-2.23.0.dist-info/top_level.txt
thousandeyes_sdk_endpoint_tests-2.23.0.dist-info/RECORD
